<annotation>
	<folder>src</folder>
	<filename>20190121_131401_5.jpg</filename>
	<path>D:\src\20190121_131401_5.jpg</path>
	<source>
		<database>Unknown</database>
	</source>
	<size>
		<width>680</width>
		<height>590</height>
		<depth>3</depth>
	</size>
	<segmented>0</segmented>
	<object>
		<name>wcq-JinZhenGu</name>
		<pose>Unspecified</pose>
		<truncated>0</truncated>
		<difficult>0</difficult>
		<bndbox>
			<xmin>367</xmin>
			<ymin>234</ymin>
			<xmax>546</xmax>
			<ymax>421</ymax>
		</bndbox>
	</object>
	<object>
		<name>wcq-XiGua</name>
		<pose>Unspecified</pose>
		<truncated>0</truncated>
		<difficult>0</difficult>
		<bndbox>
			<xmin>108</xmin>
			<ymin>146</ymin>
			<xmax>364</xmax>
			<ymax>314</ymax>
		</bndbox>
	</object>
	<object>
		<name>wcq-CuiPiDouFu</name>
		<pose>Unspecified</pose>
		<truncated>0</truncated>
		<difficult>0</difficult>
		<bndbox>
			<xmin>88</xmin>
			<ymin>344</ymin>
			<xmax>271</xmax>
			<ymax>500</ymax>
		</bndbox>
	</object>
	<object>
		<name>wcq-MaLanTouChaoDouGan</name>
		<pose>Unspecified</pose>
		<truncated>0</truncated>
		<difficult>0</difficult>
		<bndbox>
			<xmin>249</xmin>
			<ymin>401</ymin>
			<xmax>447</xmax>
			<ymax>566</ymax>
		</bndbox>
	</object>
</annotation>
