<annotation>
	<folder>src</folder>
	<filename>20190124_125805_8.jpg</filename>
	<path>D:\src\20190124_125805_8.jpg</path>
	<source>
		<database>Unknown</database>
	</source>
	<size>
		<width>680</width>
		<height>590</height>
		<depth>3</depth>
	</size>
	<segmented>0</segmented>
	<object>
		<name>wcq-ShanYao</name>
		<pose>Unspecified</pose>
		<truncated>0</truncated>
		<difficult>0</difficult>
		<bndbox>
			<xmin>288</xmin>
			<ymin>366</ymin>
			<xmax>442</xmax>
			<ymax>542</ymax>
		</bndbox>
	</object>
	<object>
		<name>wcq-MuErWanZi</name>
		<pose>Unspecified</pose>
		<truncated>0</truncated>
		<difficult>0</difficult>
		<bndbox>
			<xmin>104</xmin>
			<ymin>247</ymin>
			<xmax>278</xmax>
			<ymax>425</ymax>
		</bndbox>
	</object>
	<object>
		<name>wcq-SiJiDouChaoRou</name>
		<pose>Unspecified</pose>
		<truncated>0</truncated>
		<difficult>0</difficult>
		<bndbox>
			<xmin>253</xmin>
			<ymin>133</ymin>
			<xmax>476</xmax>
			<ymax>307</ymax>
		</bndbox>
	</object>
	<object>
		<name>wcq-YouPaoRouPian</name>
		<pose>Unspecified</pose>
		<truncated>0</truncated>
		<difficult>0</difficult>
		<bndbox>
			<xmin>415</xmin>
			<ymin>263</ymin>
			<xmax>584</xmax>
			<ymax>452</ymax>
		</bndbox>
	</object>
</annotation>
