<annotation>
	<folder>src</folder>
	<filename>20190117_113143_2.jpg</filename>
	<path>C:\Users\Administrator\Desktop\src\20190117_113143_2.jpg</path>
	<source>
		<database>Unknown</database>
	</source>
	<size>
		<width>680</width>
		<height>590</height>
		<depth>3</depth>
	</size>
	<segmented>0</segmented>
	<object>
		<name>wcq-DongZhuPi</name>
		<pose>Unspecified</pose>
		<truncated>0</truncated>
		<difficult>0</difficult>
		<bndbox>
			<xmin>154</xmin>
			<ymin>388</ymin>
			<xmax>347</xmax>
			<ymax>547</ymax>
		</bndbox>
	</object>
	<object>
		<name>wcq-DongZhuPi</name>
		<pose>Unspecified</pose>
		<truncated>0</truncated>
		<difficult>0</difficult>
		<bndbox>
			<xmin>298</xmin>
			<ymin>245</ymin>
			<xmax>487</xmax>
			<ymax>416</ymax>
		</bndbox>
	</object>
	<object>
		<name>wcq-DongZhuPi</name>
		<pose>Unspecified</pose>
		<truncated>0</truncated>
		<difficult>0</difficult>
		<bndbox>
			<xmin>187</xmin>
			<ymin>135</ymin>
			<xmax>368</xmax>
			<ymax>288</ymax>
		</bndbox>
	</object>
	<object>
		<name>wcq-DongZhuPi</name>
		<pose>Unspecified</pose>
		<truncated>0</truncated>
		<difficult>0</difficult>
		<bndbox>
			<xmin>34</xmin>
			<ymin>262</ymin>
			<xmax>219</xmax>
			<ymax>435</ymax>
		</bndbox>
	</object>
</annotation>
