<annotation>
	<folder>src</folder>
	<filename>20190430_164138_11.jpg</filename>
	<path>D:\src\20190430_164138_11.jpg</path>
	<source>
		<database>Unknown</database>
	</source>
	<size>
		<width>690</width>
		<height>550</height>
		<depth>3</depth>
	</size>
	<segmented>0</segmented>
	<object>
		<name>JYsf-Xiao_Tang_Wan</name>
		<pose>Unspecified</pose>
		<truncated>1</truncated>
		<difficult>0</difficult>
		<bndbox>
			<xmin>186</xmin>
			<ymin>262</ymin>
			<xmax>487</xmax>
			<ymax>550</ymax>
		</bndbox>
	</object>
	<object>
		<name>JYsf-Shuang_Er_Pan</name>
		<pose>Unspecified</pose>
		<truncated>0</truncated>
		<difficult>0</difficult>
		<bndbox>
			<xmin>382</xmin>
			<ymin>77</ymin>
			<xmax>598</xmax>
			<ymax>320</ymax>
		</bndbox>
	</object>
	<object>
		<name>JYsf-Ao_Yuan_Wan</name>
		<pose>Unspecified</pose>
		<truncated>0</truncated>
		<difficult>0</difficult>
		<bndbox>
			<xmin>70</xmin>
			<ymin>95</ymin>
			<xmax>275</xmax>
			<ymax>309</ymax>
		</bndbox>
	</object>
</annotation>
