<annotation>
	<folder>src</folder>
	<filename>20190430_123511_10.jpg</filename>
	<path>C:\Users\Administrator\Desktop\src\20190430_123511_10.jpg</path>
	<source>
		<database>Unknown</database>
	</source>
	<size>
		<width>690</width>
		<height>550</height>
		<depth>3</depth>
	</size>
	<segmented>0</segmented>
	<object>
		<name>JYsf-Xiao_Tang_Wan</name>
		<pose>Unspecified</pose>
		<truncated>0</truncated>
		<difficult>0</difficult>
		<bndbox>
			<xmin>8</xmin>
			<ymin>19</ymin>
			<xmax>302</xmax>
			<ymax>320</ymax>
		</bndbox>
	</object>
	<object>
		<name>JYsf-Ao_Yuan_Wan</name>
		<pose>Unspecified</pose>
		<truncated>0</truncated>
		<difficult>0</difficult>
		<bndbox>
			<xmin>444</xmin>
			<ymin>189</ymin>
			<xmax>636</xmax>
			<ymax>391</ymax>
		</bndbox>
	</object>
	<object>
		<name>JYsf-Shuang_Er_Pan</name>
		<pose>Unspecified</pose>
		<truncated>0</truncated>
		<difficult>0</difficult>
		<bndbox>
			<xmin>175</xmin>
			<ymin>275</ymin>
			<xmax>429</xmax>
			<ymax>500</ymax>
		</bndbox>
	</object>
</annotation>
