<annotation>
	<folder>src</folder>
	<filename>20190505_160404_18.jpg</filename>
	<path>E:\label3\src\20190505_160404_18.jpg</path>
	<source>
		<database>Unknown</database>
	</source>
	<size>
		<width>680</width>
		<height>520</height>
		<depth>3</depth>
	</size>
	<segmented>0</segmented>
	<object>
		<name>JYsf-Mian_Pan</name>
		<pose>Unspecified</pose>
		<truncated>0</truncated>
		<difficult>0</difficult>
		<bndbox>
			<xmin>260</xmin>
			<ymin>162</ymin>
			<xmax>586</xmax>
			<ymax>473</ymax>
		</bndbox>
	</object>
	<object>
		<name>JYsf-Tuo_Yuan_Wan</name>
		<pose>Unspecified</pose>
		<truncated>0</truncated>
		<difficult>0</difficult>
		<bndbox>
			<xmin>46</xmin>
			<ymin>145</ymin>
			<xmax>240</xmax>
			<ymax>429</ymax>
		</bndbox>
	</object>
</annotation>
