<annotation>
	<folder>src</folder>
	<filename>20190604_151939_35.jpg</filename>
	<path>D:\src\20190604_151939_35.jpg</path>
	<source>
		<database>Unknown</database>
	</source>
	<size>
		<width>720</width>
		<height>510</height>
		<depth>3</depth>
	</size>
	<segmented>0</segmented>
	<object>
		<name>JYsf-Xiao_Tang_Wan</name>
		<pose>Unspecified</pose>
		<truncated>0</truncated>
		<difficult>0</difficult>
		<bndbox>
			<xmin>47</xmin>
			<ymin>114</ymin>
			<xmax>348</xmax>
			<ymax>416</ymax>
		</bndbox>
	</object>
	<object>
		<name>JYsf-Da_Yuan_Pan</name>
		<pose>Unspecified</pose>
		<truncated>0</truncated>
		<difficult>0</difficult>
		<bndbox>
			<xmin>296</xmin>
			<ymin>107</ymin>
			<xmax>641</xmax>
			<ymax>466</ymax>
		</bndbox>
	</object>
</annotation>
